terminalutilities/__init__.py
terminalutilities/terminalutilities.py
terminalutilities-0.0.7.dist-info/LICENSE
terminalutilities-0.0.7.dist-info/METADATA
terminalutilities-0.0.7.dist-info/WHEEL
terminalutilities-0.0.7.dist-info/top_level.txt
terminalutilities-0.0.7.dist-info/RECORD
