Metadata-Version: 2.1
Name: terminalutilities
Version: 0.0.7
Summary: A set of utilities for use in a terminal
Home-page: https://github.com/kedymera/terminalutilities
Author: Kedymera
Author-email: kedymera@gmail.com
License: UNKNOWN
Project-URL: Bug Tracker, https://github.com/kedymera/terminalutilities/issues
Platform: UNKNOWN
Classifier: Programming Language :: Python :: 3
Classifier: Operating System :: OS Independent
Classifier: Intended Audience :: Developers
Classifier: License :: OSI Approved :: GNU General Public License v3 (GPLv3)
Requires-Python: >=3.6
License-File: LICENSE
